<annotation>
	<folder>images</folder>
	<filename>run10-17.jpg</filename>
	<path>/Users/rishavrajendra/Downloads/images/run10-17.jpg</path>
	<source>
		<database>Unknown</database>
	</source>
	<size>
		<width>300</width>
		<height>300</height>
		<depth>3</depth>
	</size>
	<segmented>0</segmented>
	<object>
		<name>obstacle</name>
		<pose>Unspecified</pose>
		<truncated>0</truncated>
		<difficult>0</difficult>
		<bndbox>
			<xmin>145</xmin>
			<ymin>61</ymin>
			<xmax>161</xmax>
			<ymax>97</ymax>
		</bndbox>
	</object>
	<object>
		<name>obstacle</name>
		<pose>Unspecified</pose>
		<truncated>0</truncated>
		<difficult>0</difficult>
		<bndbox>
			<xmin>215</xmin>
			<ymin>56</ymin>
			<xmax>231</xmax>
			<ymax>83</ymax>
		</bndbox>
	</object>
	<object>
		<name>obstacle</name>
		<pose>Unspecified</pose>
		<truncated>0</truncated>
		<difficult>0</difficult>
		<bndbox>
			<xmin>251</xmin>
			<ymin>43</ymin>
			<xmax>261</xmax>
			<ymax>63</ymax>
		</bndbox>
	</object>
	</annotation>