<annotation>
	<folder>images</folder>
	<filename>run2-44.jpg</filename>
	<path>/Users/rishavrajendra/Documents/images/run2-44.jpg</path>
	<source>
		<database>Unknown</database>
	</source>
	<size>
		<width>800</width>
		<height>600</height>
		<depth>3</depth>
	</size>
	<segmented>0</segmented>
	<object>
		<name>blockC</name>
		<pose>Unspecified</pose>
		<truncated>1</truncated>
		<difficult>0</difficult>
		<bndbox>
			<xmin>660</xmin>
			<ymin>527</ymin>
			<xmax>798</xmax>
			<ymax>600</ymax>
		</bndbox>
	</object>
	<object>
		<name>obstacle</name>
		<pose>Unspecified</pose>
		<truncated>1</truncated>
		<difficult>0</difficult>
		<bndbox>
			<xmin>770</xmin>
			<ymin>112</ymin>
			<xmax>800</xmax>
			<ymax>177</ymax>
		</bndbox>
	</object>
	<object>
		<name>blockB</name>
		<pose>Unspecified</pose>
		<truncated>0</truncated>
		<difficult>0</difficult>
		<bndbox>
			<xmin>553</xmin>
			<ymin>184</ymin>
			<xmax>607</xmax>
			<ymax>229</ymax>
		</bndbox>
	</object>
	<object>
		<name>corner</name>
		<pose>Unspecified</pose>
		<truncated>0</truncated>
		<difficult>0</difficult>
		<bndbox>
			<xmin>261</xmin>
			<ymin>34</ymin>
			<xmax>302</xmax>
			<ymax>132</ymax>
		</bndbox>
	</object>
</annotation>
