<annotation>
	<folder>SuzuBatch</folder>
	<filename>run6-86.jpg</filename>
	<path>C:\Users\Suzu\Desktop\SuzuBatch\SuzuBatch\run6-86.jpg</path>
	<source>
		<database>Unknown</database>
	</source>
	<size>
		<width>800</width>
		<height>600</height>
		<depth>3</depth>
	</size>
	<segmented>0</segmented>
	<object>
		<name>corner</name>
		<pose>Unspecified</pose>
		<truncated>0</truncated>
		<difficult>0</difficult>
		<bndbox>
			<xmin>721</xmin>
			<ymin>2</ymin>
			<xmax>762</xmax>
			<ymax>70</ymax>
		</bndbox>
	</object>
	<object>
		<name>blockB</name>
		<pose>Unspecified</pose>
		<truncated>0</truncated>
		<difficult>0</difficult>
		<bndbox>
			<xmin>625</xmin>
			<ymin>64</ymin>
			<xmax>654</xmax>
			<ymax>90</ymax>
		</bndbox>
	</object>
	<object>
		<name>blockE</name>
		<pose>Unspecified</pose>
		<truncated>0</truncated>
		<difficult>0</difficult>
		<bndbox>
			<xmin>707</xmin>
			<ymin>99</ymin>
			<xmax>743</xmax>
			<ymax>139</ymax>
		</bndbox>
	</object>
	<object>
		<name>blockC</name>
		<pose>Unspecified</pose>
		<truncated>0</truncated>
		<difficult>0</difficult>
		<bndbox>
			<xmin>575</xmin>
			<ymin>304</ymin>
			<xmax>669</xmax>
			<ymax>421</ymax>
		</bndbox>
	</object>
	<object>
		<name>start</name>
		<pose>Unspecified</pose>
		<truncated>0</truncated>
		<difficult>0</difficult>
		<bndbox>
			<xmin>282</xmin>
			<ymin>206</ymin>
			<xmax>363</xmax>
			<ymax>241</ymax>
		</bndbox>
	</object>
	<object>
		<name>slope</name>
		<pose>Unspecified</pose>
		<truncated>1</truncated>
		<difficult>0</difficult>
		<bndbox>
			<xmin>674</xmin>
			<ymin>153</ymin>
			<xmax>800</xmax>
			<ymax>246</ymax>
		</bndbox>
	</object>
</annotation>
