<annotation>
	<folder>run6 150-255</folder>
	<filename>run6-217.jpg</filename>
	<path>C:\Users\Tony\Desktop\run6 150-255\run6-217.jpg</path>
	<source>
		<database>Unknown</database>
	</source>
	<size>
		<width>800</width>
		<height>600</height>
		<depth>3</depth>
	</size>
	<segmented>0</segmented>
	<object>
		<name>blockC</name>
		<pose>Unspecified</pose>
		<truncated>1</truncated>
		<difficult>0</difficult>
		<bndbox>
			<xmin>1</xmin>
			<ymin>268</ymin>
			<xmax>164</xmax>
			<ymax>488</ymax>
		</bndbox>
	</object>
	<object>
		<name>slope</name>
		<pose>Unspecified</pose>
		<truncated>1</truncated>
		<difficult>0</difficult>
		<bndbox>
			<xmin>728</xmin>
			<ymin>1</ymin>
			<xmax>800</xmax>
			<ymax>81</ymax>
		</bndbox>
	</object>
</annotation>
