<annotation>
	<folder>run6 150-255</folder>
	<filename>run6-105.jpg</filename>
	<path>C:\Users\Tony\Desktop\run6 150-255\run6-105.jpg</path>
	<source>
		<database>Unknown</database>
	</source>
	<size>
		<width>800</width>
		<height>600</height>
		<depth>3</depth>
	</size>
	<segmented>0</segmented>
	<object>
		<name>blockB</name>
		<pose>Unspecified</pose>
		<truncated>0</truncated>
		<difficult>0</difficult>
		<bndbox>
			<xmin>701</xmin>
			<ymin>95</ymin>
			<xmax>778</xmax>
			<ymax>130</ymax>
		</bndbox>
	</object>
	<object>
		<name>corner</name>
		<pose>Unspecified</pose>
		<truncated>0</truncated>
		<difficult>0</difficult>
		<bndbox>
			<xmin>666</xmin>
			<ymin>8</ymin>
			<xmax>737</xmax>
			<ymax>83</ymax>
		</bndbox>
	</object>
</annotation>
