<annotation>
	<folder>benji</folder>
	<filename>run9-67.jpg</filename>
	<path>/home/benji/Desktop/benji/run9-67.jpg</path>
	<source>
		<database>Unknown</database>
	</source>
	<size>
		<width>300</width>
		<height>300</height>
		<depth>3</depth>
	</size>
	<segmented>0</segmented>
	<object>
		<name>obstacle</name>
		<pose>Unspecified</pose>
		<truncated>1</truncated>
		<difficult>0</difficult>
		<bndbox>
			<xmin>1</xmin>
			<ymin>46</ymin>
			<xmax>17</xmax>
			<ymax>80</ymax>
		</bndbox>
	</object>
	<object>
		<name>obstacle</name>
		<pose>Unspecified</pose>
		<truncated>0</truncated>
		<difficult>0</difficult>
		<bndbox>
			<xmin>89</xmin>
			<ymin>47</ymin>
			<xmax>104</xmax>
			<ymax>75</ymax>
		</bndbox>
	</object>
	<object>
		<name>obstacle</name>
		<pose>Unspecified</pose>
		<truncated>0</truncated>
		<difficult>0</difficult>
		<bndbox>
			<xmin>171</xmin>
			<ymin>41</ymin>
			<xmax>180</xmax>
			<ymax>60</ymax>
		</bndbox>
	</object>
	<object>
		<name>obstacle</name>
		<pose>Unspecified</pose>
		<truncated>1</truncated>
		<difficult>0</difficult>
		<bndbox>
			<xmin>67</xmin>
			<ymin>222</ymin>
			<xmax>148</xmax>
			<ymax>300</ymax>
		</bndbox>
	</object>
	<object>
		<name>start</name>
		<pose>Unspecified</pose>
		<truncated>0</truncated>
		<difficult>0</difficult>
		<bndbox>
			<xmin>95</xmin>
			<ymin>140</ymin>
			<xmax>168</xmax>
			<ymax>173</ymax>
		</bndbox>
	</object>
	<object>
		<name>blockA</name>
		<pose>Unspecified</pose>
		<truncated>0</truncated>
		<difficult>0</difficult>
		<bndbox>
			<xmin>198</xmin>
			<ymin>73</ymin>
			<xmax>217</xmax>
			<ymax>86</ymax>
		</bndbox>
	</object>
	<object>
		<name>corner</name>
		<pose>Unspecified</pose>
		<truncated>0</truncated>
		<difficult>0</difficult>
		<bndbox>
			<xmin>211</xmin>
			<ymin>18</ymin>
			<xmax>227</xmax>
			<ymax>50</ymax>
		</bndbox>
	</object>
	<object>
		<name>slope</name>
		<pose>Unspecified</pose>
		<truncated>0</truncated>
		<difficult>0</difficult>
		<bndbox>
			<xmin>221</xmin>
			<ymin>59</ymin>
			<xmax>254</xmax>
			<ymax>73</ymax>
		</bndbox>
	</object>
	<object>
		<name>side</name>
		<pose>Unspecified</pose>
		<truncated>1</truncated>
		<difficult>0</difficult>
		<bndbox>
			<xmin>258</xmin>
			<ymin>66</ymin>
			<xmax>300</xmax>
			<ymax>82</ymax>
		</bndbox>
	</object>
</annotation>
